<annotation>
  <folder>0268</folder>
  <filename>0268_normal_peep_C.jpg</filename>
  <source>
    <database>Unknown</database>
    <annotation>Unknown</annotation>
    <image>Unknown</image>
  </source>
  <size>
    <width>800</width>
    <height>177</height>
    <depth></depth>
  </size>
  <segmented>0</segmented>
  <object>
    <name>normal_volume</name>
    <truncated>0</truncated>
    <occluded>0</occluded>
    <difficult>0</difficult>
    <bndbox>
      <xmin>19.4</xmin>
      <ymin>2.55</ymin>
      <xmax>755.97</xmax>
      <ymax>176.04</ymax>
    </bndbox>
    <attributes>
      <attribute>
        <name>rotation</name>
        <value>0.0</value>
      </attribute>
    </attributes>
  </object>
</annotation>
